redshift_user_manager/__init__.py
redshift_user_manager/cli.py
redshift_user_manager/constants.py
redshift_user_manager/exceptions.py
redshift_user_manager/py.typed
redshift_user_manager/redshift_user_manager.py
redshift_user_manager-0.1.3.dist-info/LICENSE
redshift_user_manager-0.1.3.dist-info/METADATA
redshift_user_manager-0.1.3.dist-info/WHEEL
redshift_user_manager-0.1.3.dist-info/entry_points.txt
redshift_user_manager-0.1.3.dist-info/top_level.txt
redshift_user_manager-0.1.3.dist-info/RECORD
