Metadata-Version: 2.1
Name: redshift-user-manager
Version: 0.1.3
Summary: A user management CLI tool for AWS Redshift.
Home-page: https://github.com/henryivesjones/redshift-user-manager
Author: Henry Jones
Author-email: Henry Jones <henryivesjones@gmail.com>
License: GPL-3.0-or-later
Keywords: sql,redshift,user,managment
Classifier: License :: OSI Approved :: GNU General Public License v3 or later (GPLv3+)
Classifier: Programming Language :: Python :: 3
Classifier: Programming Language :: Python :: 3.7
Classifier: Programming Language :: Python :: 3.8
Classifier: Programming Language :: Python :: 3.9
Classifier: Programming Language :: Python :: 3.10
Classifier: Programming Language :: Python :: 3.11
Requires-Python: >=3.6
License-File: LICENSE
Requires-Dist: pydantic
Requires-Dist: pyyaml
Requires-Dist: asyncpg (==0.27.0)
Requires-Dist: click (>=8.0.0)
